flicamera/libfli.cpython-39-x86_64-linux-gnu.so
flicamera/actor.py
flicamera/__init__.py
flicamera/__main__.py
flicamera/libfli.cpython-38-x86_64-linux-gnu.so
flicamera/libfli.cpython-310-x86_64-linux-gnu.so
flicamera/lib.py
flicamera/mock.py
flicamera/camera.py
flicamera/model.py
flicamera/etc/flicamera.yaml
sdss_flicamera-0.6.0.dist-info/entry_points.txt
sdss_flicamera-0.6.0.dist-info/LICENSE.md
sdss_flicamera-0.6.0.dist-info/RECORD
sdss_flicamera-0.6.0.dist-info/METADATA
sdss_flicamera-0.6.0.dist-info/WHEEL
sdss_flicamera.libs/libudev-8edd2273.so.1.6.2
sdss_flicamera.libs/libbz2-a273e504.so.1.0.6
sdss_flicamera.libs/libcap-79733b59.so.2.22
sdss_flicamera.libs/libdw-0-780627ce.176.so
sdss_flicamera.libs/libattr-4f2a9577.so.1.1.0
sdss_flicamera.libs/liblzma-004595ca.so.5.2.2
sdss_flicamera.libs/libusb-1-150b88da.0.so.0.1.0
sdss_flicamera.libs/libelf-0-3d9de92a.176.so
