Metadata-Version: 2.1
Name: sdss-flicamera
Version: 0.6.0
Summary: A library to control Finger Lakes Instrumentation cameras.
Home-page: https://github.com/sdss/flicamera
License: BSD-3-Clause
Keywords: astronomy,software
Author: José Sánchez-Gallego
Author-email: gallegoj@uw.edu
Requires-Python: >=3.8,<4.0
Classifier: Development Status :: 4 - Beta
Classifier: Intended Audience :: Science/Research
Classifier: License :: OSI Approved :: BSD License
Classifier: Natural Language :: English
Classifier: Operating System :: OS Independent
Classifier: Programming Language :: Python :: 3
Classifier: Programming Language :: Python :: 3.8
Classifier: Programming Language :: Python :: 3.9
Classifier: Programming Language :: Python :: 3.10
Classifier: Programming Language :: Python :: 3.11
Classifier: Topic :: Documentation :: Sphinx
Classifier: Topic :: Software Development :: Libraries :: Python Modules
Requires-Dist: click_default_group (>=1.2.2,<2.0.0)
Requires-Dist: photutils (>=1.0.2,<2.0.0)
Requires-Dist: scipy (>=1.9.1,<2.0.0)
Requires-Dist: sdss-basecam (>=0.7.0,<0.8.0)
Requires-Dist: sdsstools (>=0.5.2)
Project-URL: Documentation, https://sdss-flicamera.readthedocs.io/en/latest/
Project-URL: Repository, https://github.com/sdss/flicamera
